.gitignore
setup.py
pubfind/__init__.py
pubfind/__main__.py
pubfind/_fedora_doi_lookup.py
pubfind/_scopus_csv.py
pubfind/cmd.py
pubfind/config.py
pubfind/utils.py
pubfind.egg-info/PKG-INFO
pubfind.egg-info/SOURCES.txt
pubfind.egg-info/dependency_links.txt
pubfind.egg-info/entry_points.txt
pubfind.egg-info/pbr.json
pubfind.egg-info/requires.txt
pubfind.egg-info/top_level.txt
tests/__init__.py
tests/test_fedora_doi_lookup.py