Metadata-Version: 1.1
Name: pubfind
Version: 0.2.0
Summary: Publication search command line tool.
Home-page: https://github.com/jayvdb/pubfind
Author: John Vandenberg
Author-email: jayvdb@gmail.com
License: MIT
Keywords: c,s,l, ,s,c,o,p,u,s, ,c,s,v, ,j,s,o,n, ,s,c,h,e,m,a, ,p,u,b,l,i,c,a,t,i,o,n, ,a,r,t,i,c,l,e, ,j,o,u,r,n,a,l
Platform: UNKNOWN
Classifier: Development Status :: 3 - Alpha
Classifier: Environment :: Console
Classifier: License :: OSI Approved :: MIT License
Classifier: Operating System :: OS Independent
Classifier: Programming Language :: Python
Classifier: Programming Language :: Python :: 2
Classifier: Programming Language :: Python :: 3
